{
  "user": [
    {
      "name": "abbas",
      "lastName": "abbsa",
      "phone": 121212,
      "id": 1
    },
    {
      "name": "abbas",
      "lastName": "abbsa",
      "phone": 121212,
      "id": 2
    },
    {
      "name": "abbas",
      "lastName": "abbsa",
      "phone": 121212,
      "id": 4
    },
    {
      "name": "abbas",
      "lastName": "abbsa",
      "phone": 121212,
      "id": 5
    },
    {
      "name": "wer",
      "lastName": "cvbbv",
      "phone": 436524,
      "id": 6
    }
  ]
}